thorhammer/__init__.py
thorhammer/datasets.py
thorhammer/mjolnir.py
thorhammer/transforms.py
thor_hammer-0.0.10.dist-info/METADATA
thor_hammer-0.0.10.dist-info/WHEEL
thor_hammer-0.0.10.dist-info/licenses/LICENSE
thor_hammer-0.0.10.dist-info/RECORD
