Metadata-Version: 2.1
Name: Thor-Hammer
Version: 0.0.10
Summary: Defeating causal dragons with interpretable machine learning informed by causal assumptions.
Project-URL: Homepage, https://github.com/galenseilis/Mjolnir
Project-URL: Bug Tracker, https://github.com/galenseilis/Mjolnir/issues
Author-email: Galen Seilis <galen.seilis@seilis.ca>
License-File: LICENSE
Classifier: License :: OSI Approved :: GNU General Public License v3 or later (GPLv3+)
Classifier: Operating System :: OS Independent
Classifier: Programming Language :: Python :: 3
Requires-Python: >=3.7
Requires-Dist: gplearn
Requires-Dist: mapie
Requires-Dist: networkx
Requires-Dist: numpy
Requires-Dist: pandas
Requires-Dist: scikit-learn
Requires-Dist: sympy
